keyvalues1/__init__.py
keyvalues1/parser.py
keyvalues1/py.typed
keyvalues1/transformers.py
keyvalues1/types.py
keyvalues1-2.1.0.dist-info/METADATA
keyvalues1-2.1.0.dist-info/WHEEL
keyvalues1-2.1.0.dist-info/licenses/LICENSE
keyvalues1-2.1.0.dist-info/RECORD
